{"__symbolic":"module","version":4,"metadata":{"CovalentGuidedTourModule":{"__symbolic":"class","decorators":[{"__symbolic":"call","expression":{"__symbolic":"reference","module":"@angular/core","name":"NgModule","line":4,"character":1},"arguments":[{"imports":[{"__symbolic":"reference","module":"@angular/common","name":"CommonModule","line":5,"character":12}],"providers":[{"__symbolic":"reference","name":"CovalentGuidedTourService"}],"declarations":[],"exports":[]}]}],"members":{}},"IGuidedTour":{"__symbolic":"interface"},"IGuidedTourStep":{"__symbolic":"interface"},"CovalentGuidedTourService":{"__symbolic":"class","extends":{"__symbolic":"reference","name":"CovalentGuidedTour"},"decorators":[{"__symbolic":"call","expression":{"__symbolic":"reference","module":"@angular/core","name":"Injectable","line":31,"character":1}}],"members":{"__ctor__":[{"__symbolic":"constructor","parameters":[{"__symbolic":"reference","module":"@angular/router","name":"Router","line":35,"character":31},{"__symbolic":"reference","module":"@angular/router","name":"ActivatedRoute","line":35,"character":55},{"__symbolic":"reference","module":"@angular/common/http","name":"HttpClient","line":35,"character":92}]}],"registerTour":[{"__symbolic":"method"}],"startTour":[{"__symbolic":"method"}],"initializeOnQueryParams":[{"__symbolic":"method"}],"_loadTour":[{"__symbolic":"method"}],"_getTour":[{"__symbolic":"method"}],"_configureRoutesForSteps":[{"__symbolic":"method"}]}},"TourStep":{"__symbolic":"interface"},"TourStepButton":{"__symbolic":"interface"},"ITourEventOn":{"__symbolic":"interface"},"ITourEventOnOptions":{"__symbolic":"interface"},"ITourAbortOn":{"__symbolic":"interface"},"ITourOptions":{"__symbolic":"interface"},"ITourStepAttachToOptions":{"__symbolic":"interface"},"ITourStepAdvanceOn":{"__symbolic":"interface"},"ITourStepAdvanceOnOptions":{"__symbolic":"interface"},"ITourStep":{"__symbolic":"interface"},"CovalentGuidedTour":{"__symbolic":"class","extends":{"__symbolic":"error","message":"Reference to non-exported class","line":53,"character":0,"context":{"className":"TourButtonsActions"},"module":"./guided.tour"},"members":{"__ctor__":[{"__symbolic":"constructor","parameters":[{"__symbolic":"reference","name":"any"}]}],"newTour":[{"__symbolic":"method"}],"back":[{"__symbolic":"method"}],"cancel":[{"__symbolic":"method"}],"next":[{"__symbolic":"method"}],"finish":[{"__symbolic":"method"}],"addSteps":[{"__symbolic":"method"}],"start":[{"__symbolic":"method"}],"_prepareTour":[{"__symbolic":"method"}],"_bindEvent":[{"__symbolic":"method"}]}}},"origins":{"CovalentGuidedTourModule":"./guided-tour.module","IGuidedTour":"./guided-tour.service","IGuidedTourStep":"./guided-tour.service","CovalentGuidedTourService":"./guided-tour.service","TourStep":"./guided.tour","TourStepButton":"./guided.tour","ITourEventOn":"./guided.tour","ITourEventOnOptions":"./guided.tour","ITourAbortOn":"./guided.tour","ITourOptions":"./guided.tour","ITourStepAttachToOptions":"./guided.tour","ITourStepAdvanceOn":"./guided.tour","ITourStepAdvanceOnOptions":"./guided.tour","ITourStep":"./guided.tour","CovalentGuidedTour":"./guided.tour"},"importAs":"@covalent/guided-tour"}